{"pageDepth":2,"statusbar":"【美化开关】【网页美化】","beginning":"","regex_scripts":[{"id":-1,"replaceString":"<div class=\"teapot-sidebar-romance\" onclick=\"event.stopPropagation()\" style=\"position:fixed;left:0;top:35%;transform:translateY(-50%);display:flex;flex-direction:column;gap:10px;z-index:99999;\">\n    <div class=\"teapot-btn-romance\" onclick=\"event.stopPropagation();\n        const s = document.getElementById('hu-beauty-style-cold-full');\n        if (s) {\n            const root = document.documentElement;\n            // 每套主题均配专属图标滤镜色，严格按JSON格式：invert+sepia+saturate+hue-rotate+brightness+contrast\n            if (this.innerText === '美化开') {\n                // 1.冷蓝调 - 蓝系滤镜+配套侧边栏\n                root.style.setProperty('--l-bg', 'rgb(216,224,236)');\n                root.style.setProperty('--l-card', 'rgb(245,248,252)');\n                root.style.setProperty('--l-card-me', 'rgb(218,226,240)');\n                root.style.setProperty('--l-main', 'rgb(79,90,169)');\n                root.style.setProperty('--l-line', 'rgb(106,156,196)');\n                root.style.setProperty('--l-text', 'rgb(58,30,28)');\n                root.style.setProperty('--l-sub', 'rgb(106,112,133)');\n                root.style.setProperty('--light-color', 'rgba(150,180,245,0.6)');\n                root.style.setProperty('--light-deep', 'rgba(79,90,169,0.7)');\n                // 修正：滤镜值后去掉!important，第三个参数传'important'（JS标准写法）\n                root.style.setProperty('--blue-filter', 'invert(25%) sepia(80%) saturate(1800%) hue-rotate(200deg) brightness(90%) contrast(95%)', 'important');\n                root.style.setProperty('--input-gradient', 'linear-gradient(135deg, rgb(248,250,253) 0%, rgb(238,242,248) 50%, rgb(228,234,242) 100%)');\n                root.style.setProperty('--input-gradient-hover', 'linear-gradient(135deg, rgb(250,252,254) 0%, rgb(242,246,250) 50%, rgb(232,238,246) 100%)');\n                this.style.backgroundColor = '#A0D0F0';\n                this.style.borderColor = '#2060A0';\n                this.innerText = '冷蓝调';\n            } else if (this.innerText === '冷蓝调') {\n                // 2.红棕调（原青橙调）- 暗红系全套配色\n                root.style.setProperty('--l-bg', 'rgb(40,25,28)');\n                root.style.setProperty('--l-card', 'rgb(65,35,40)');\n                root.style.setProperty('--l-card-me', 'rgb(85,40,48)');\n                root.style.setProperty('--l-main', 'rgb(180,60,75)');\n                root.style.setProperty('--l-line', 'rgb(140,45,58)');\n                root.style.setProperty('--l-text', 'rgb(235,220,222)');\n                root.style.setProperty('--l-sub', 'rgb(185,165,168)');\n                root.style.setProperty('--light-color', 'rgba(180,60,75,0.6)');\n                root.style.setProperty('--light-deep', 'rgba(140,45,58,0.7)');\n                root.style.setProperty('--blue-filter', 'invert(18%) sepia(90%) saturate(2800%) hue-rotate(355deg) brightness(88%) contrast(95%)', 'important');\n                root.style.setProperty('--input-gradient', 'linear-gradient(135deg, rgb(70,38,42) 0%, rgb(60,32,36) 50%, rgb(50,26,30) 100%)');\n                root.style.setProperty('--input-gradient-hover', 'linear-gradient(135deg, rgb(80,42,48) 0%, rgb(70,38,42) 50%, rgb(60,32,36) 100%)');\n                this.style.backgroundColor = '#b84c58';\n                this.style.borderColor = '#802c38';\n                this.innerText = '红棕调';\n            } else if (this.innerText === '红棕调') {\n                // 3.紫粉调 - 紫粉滤镜+配套侧边栏\n                root.style.setProperty('--l-bg', 'rgb(236,216,224)');\n                root.style.setProperty('--l-card', 'rgb(252,245,248)');\n                root.style.setProperty('--l-card-me', 'rgb(240,218,226)');\n                root.style.setProperty('--l-main', 'rgb(169,79,169)');\n                root.style.setProperty('--l-line', 'rgb(196,106,156)');\n                root.style.setProperty('--l-text', 'rgb(58,28,58)');\n                root.style.setProperty('--l-sub', 'rgb(133,106,112)');\n                root.style.setProperty('--light-color', 'rgba(245,150,180,0.6)');\n                root.style.setProperty('--light-deep', 'rgba(169,79,169,0.7)');\n                root.style.setProperty('--blue-filter', 'invert(25%) sepia(80%) saturate(1800%) hue-rotate(280deg) brightness(90%) contrast(95%)', 'important');\n                root.style.setProperty('--input-gradient', 'linear-gradient(135deg, rgb(252,248,250) 0%, rgb(248,238,242) 50%, rgb(242,228,234) 100%)');\n                root.style.setProperty('--input-gradient-hover', 'linear-gradient(135deg, rgb(254,250,252) 0%, rgb(250,240,244) 50%, rgb(246,232,236) 100%)');\n                this.style.backgroundColor = '#D8A8E8';\n                this.style.borderColor = '#8040A0';\n                this.innerText = '紫粉调';\n            } else if (this.innerText === '紫粉调') {\n                // 4.黑白调 - 黑白滤镜+配套侧边栏\n                root.style.setProperty('--l-bg', 'rgb(220,220,220)');\n                root.style.setProperty('--l-card', 'rgb(255,255,255)');\n                root.style.setProperty('--l-card-me', 'rgb(240,240,240)');\n                root.style.setProperty('--l-main', 'rgb(80,80,80)');\n                root.style.setProperty('--l-line', 'rgb(120,120,120)');\n                root.style.setProperty('--l-text', 'rgb(20,20,20)');\n                root.style.setProperty('--l-sub', 'rgb(120,120,120)');\n                root.style.setProperty('--light-color', 'rgba(180,180,180,0.6)');\n                root.style.setProperty('--light-deep', 'rgba(80,80,80,0.7)');\n                root.style.setProperty('--blue-filter', 'grayscale(100%)', 'important');\n                root.style.setProperty('--input-gradient', 'linear-gradient(135deg, rgb(255,255,255) 0%, rgb(245,245,245) 50%, rgb(235,235,235) 100%)');\n                root.style.setProperty('--input-gradient-hover', 'linear-gradient(135deg, rgb(255,255,255) 0%, rgb(248,248,248) 50%, rgb(240,240,240) 100%)');\n                this.style.backgroundColor = '#C0C0C0';\n                this.style.borderColor = '#606060';\n                this.innerText = '黑白调';\n            } else if (this.innerText === '黑白调') {\n                // 5.绿调 - 绿系滤镜+配套侧边栏\n                root.style.setProperty('--l-bg', 'rgb(224,236,216)');\n                root.style.setProperty('--l-card', 'rgb(248,252,245)');\n                root.style.setProperty('--l-card-me', 'rgb(226,240,218)');\n                root.style.setProperty('--l-main', 'rgb(90,169,79)');\n                root.style.setProperty('--l-line', 'rgb(156,196,106)');\n                root.style.setProperty('--l-text', 'rgb(30,58,28)');\n                root.style.setProperty('--l-sub', 'rgb(112,133,106)');\n                root.style.setProperty('--light-color', 'rgba(180,245,150,0.6)');\n                root.style.setProperty('--light-deep', 'rgba(90,169,79,0.7)');\n                root.style.setProperty('--blue-filter', 'invert(25%) sepia(80%) saturate(1800%) hue-rotate(90deg) brightness(90%) contrast(95%)', 'important');\n                root.style.setProperty('--input-gradient', 'linear-gradient(135deg, rgb(249,252,247) 0%, rgb(239,248,241) 50%, rgb(229,242,233) 100%)');\n                root.style.setProperty('--input-gradient-hover', 'linear-gradient(135deg, rgb(251,254,249) 0%, rgb(243,250,243) 50%, rgb(233,246,235) 100%)');\n                this.style.backgroundColor = '#88C888';\n                this.style.borderColor = '#287828';\n                this.innerText = '绿调';\n            } else if (this.innerText === '绿调') {\n                // 6.暗红调 - 红棕滤镜（晚霞系）+ 配套侧边栏\n                root.style.setProperty('--l-bg', 'rgb(236,224,216)');\n                root.style.setProperty('--l-card', 'rgb(252,248,245)');\n                root.style.setProperty('--l-card-me', 'rgb(240,226,218)');\n                root.style.setProperty('--l-main', 'rgb(169,90,79)');\n                root.style.setProperty('--l-line', 'rgb(196,156,106)');\n                root.style.setProperty('--l-text', 'rgb(28,30,58)');\n                root.style.setProperty('--l-sub', 'rgb(133,112,106)');\n                root.style.setProperty('--light-color', 'rgba(245,180,150,0.6)');\n                root.style.setProperty('--light-deep', 'rgba(169,90,79,0.7)');\n                root.style.setProperty('--blue-filter', 'invert(25%) sepia(80%) saturate(1800%) hue-rotate(350deg) brightness(90%) contrast(95%)', 'important');\n                root.style.setProperty('--input-gradient', 'linear-gradient(135deg, rgb(252,249,246) 0%, rgb(245,234,227) 50%, rgb(236,222,214) 100%)');\n                root.style.setProperty('--input-gradient-hover', 'linear-gradient(135deg, rgb(255,254,252) 0%, rgb(248,238,232) 50%, rgb(240,226,218) 100%)');\n                this.style.backgroundColor = '#D6E4F0';\n                this.style.borderColor = '#4A6A8F';\n                this.innerText = '暗红调';\n            } else if (this.innerText === '暗红调') {\n                // 美化关闭 - 禁用样式+清空所有变量+按钮还原关的样式\n                s.disabled = true;\n                root.removeAttribute('style');\n                this.style.backgroundColor = '#F5F8FA';\n                this.style.borderColor = '#4A6A8F';\n                this.innerText = '美化关';\n            } else if (this.innerText === '美化关') {\n                // 还原原生：深海冷灰（美化开）- 用JSON原生滤镜色+所有原生变量\n                s.disabled = false;\n                s.removeAttribute('disabled');\n                root.style.setProperty('--l-bg', 'rgb(225, 230, 238)');\n                root.style.setProperty('--l-card', 'rgb(240, 245, 250)');\n                root.style.setProperty('--l-card-me', 'rgb(215, 225, 238)');\n                root.style.setProperty('--l-main', 'rgb(38, 78, 135)');\n                root.style.setProperty('--l-line', 'rgb(120, 140, 165)');\n                root.style.setProperty('--l-text', 'rgb(15, 25, 40)');\n                root.style.setProperty('--l-sub', 'rgb(80, 95, 115)');\n                root.style.setProperty('--light-color', 'rgba(80, 130, 190, 0.5)');\n                root.style.setProperty('--light-deep', 'rgba(38, 78, 135, 0.7)');\n                // 原生滤镜色按标准写法设置\n                root.style.setProperty('--blue-filter', 'invert(15%) sepia(60%) saturate(5000%) hue-rotate(260deg) brightness(85%) contrast(90%)', 'important');\n                root.style.setProperty('--input-gradient', 'linear-gradient(135deg, rgb(245, 248, 252) 0%, rgb(235, 240, 248) 50%, rgb(225, 232, 242) 100%)');\n                root.style.setProperty('--input-gradient-hover', 'linear-gradient(135deg, rgb(248, 250, 253) 0%, rgb(240, 245, 250) 50%, rgb(230, 238, 246) 100%)');\n                this.style.backgroundColor = '#D6E4F0';\n                this.style.borderColor = '#4A6A8F';\n                this.innerText = '美化开';\n            }\n        }\" \n         style=\"box-sizing:border-box;\n                width:20px;\n                padding:20px 2px;\n                height:auto;\n                background-color:#D6E4F0;\n                border:2px solid #4A6A8F;\n                border-left:none;\n                border-radius:0 8px 8px 0;\n                color:#2A3542;\n                font-size:14px;\n                letter-spacing:3px;\n                cursor:pointer;\n                writing-mode:vertical-rl;\n                text-orientation:mixed;\n                text-align:center;\n                line-height:22px;\n                transition:all 0.3s cubic-bezier(0.4,0,0.2,1);\n                box-shadow:2px 2px 6px rgba(70,100,130,0.2);\">美化开</div>\n</div>\n","scriptName":"美化开关","findRegex":"【美化开关】"},{"id":-1,"replaceString":"<style id=\"hu-beauty-style-cold-full\">\n/* ======== ❄️ 深海冷灰·静谧冷色系主题 全量优化版 ======== \n   风格：冷调静谧 · 深海灰蓝 · 高对比护眼\n   规则：全冷色系，无白色/奶白/黄色/暖色调，文字强对比\n*/\n\n:root {\n    /* --- 全局冷色系主题色 --- */\n    --l-bg: rgb(225, 230, 238);          /* 全局底色：冷调浅灰蓝 */\n    --l-card: rgb(240, 245, 250);        /* 面板通用底色：冷调浅灰 */\n    --l-card-me: rgb(215, 225, 238);     /* 自己气泡底色：冷调蓝灰 */\n    --l-main: rgb(38, 78, 135);          /* 主题主色：深海蓝（左侧粗条/点缀） */\n    --l-line: rgb(120, 140, 165);        /* 滚动条颜色：冷灰蓝 */\n    --l-text: rgb(15, 25, 40);           /* 全局主文字：深冷灰（强对比，无暖调） */\n    --l-sub: rgb(80, 95, 115);           /* 边框/次要文字：冷调中灰 */\n    --light-color: rgba(80, 130, 190, 0.5); /* 呼吸灯冷柔光 */\n    --light-deep: rgba(38, 78, 135, 0.7);   /* 呼吸灯冷深光 */\n    --blue-filter: invert(15%) sepia(60%) saturate(5000%) hue-rotate(260deg) brightness(85%) contrast(90%) !important; /* 深紫罗兰图标滤镜 */\n    --input-gradient: linear-gradient(135deg, rgb(245, 248, 252) 0%, rgb(235, 240, 248) 50%, rgb(225, 232, 242) 100%); /* 输入框冷渐变 */\n    --input-gradient-hover: linear-gradient(135deg, rgb(248, 250, 253) 0%, rgb(240, 245, 250) 50%, rgb(230, 238, 246) 100%); /* 悬停冷渐变 */\n\n    /* ---------- 👇 AI气泡专属参数 👇 ---------- */\n    --ai-text-color: rgb(15, 25, 40);    /* AI文字：深冷灰（强对比） */\n    --ai-font-size: 14px;                 /* AI字体大小 */\n    --ai-line-height: 1.5;                /* AI行高 */\n    --ai-font-weight: 700;                /* AI字体粗细700 */\n    --ai-bg: rgba(240, 245, 250, 0.8);   /* AI气泡背景：冷调半透明 */\n    --ai-border-color: var(--l-sub);      /* AI气泡边框色 */\n    --ai-left-border-color: var(--l-main);/* AI气泡左侧粗边框色 */\n    /* ---------- 👆 AI气泡专属参数 👆 ---------- */\n}\n\n\n/* ==================== 1. 全局基础样式 ==================== */\n.chat, .u-popup__content, body,\n.model-setting-scope, custom-instruction-scope, \n.history-setting-scope, .confirm-scope, .dropdown-menu, .popup-menu {\n    background-color: var(--l-bg) !important;\n    background-image: radial-gradient(rgb(215, 222, 232) 1px, transparent 1px) !important; \n    background-size: 20px 20px !important;\n    --background-color: var(--l-bg);\n    --card-background-color: var(--l-card);\n    --primary-font-color: var(--l-text);\n    font-family: \"KaiTi\", \"STKaiti\", \"SimSun\", \"Microsoft YaHei\", serif !important;\n}\n\n/* 全局通用文字样式 */\n.chat .content font, .prologue-scope .prologue-content,\n.msg-option-scope .msg-content-box, .chat .chat-bottom textarea,\n.chat .topTabbar, .history-setting-scope .title,\n.u-input__content__field-wrapper__field, .confirm-scope .ok-btn,\n.model-intro, .des-scope, .remark, .list-scope .item,\n.u-loading-icon, pre {\n    color: var(--l-text) !important;\n    text-shadow: none !important;\n    font-weight: 500 !important;\n}\n\n/* ==================== 2. 聊天气泡样式 ==================== */\n/* AI气泡 */\n.chat .chat-scope-box .scroll-view .chat-body .item .touch-scope .content.left {\n    background-color: var(--ai-bg) !important;\n    border: 2px double var(--ai-border-color) !important;\n    border-left: 5px solid var(--ai-left-border-color) !important;\n    border-radius: 5px !important;\n    color: var(--ai-text-color) !important;\n    font-size: var(--ai-font-size) !important;\n    line-height: var(--ai-line-height) !important;\n    font-weight: var(--ai-font-weight) !important;\n    box-shadow: 0 2px 4px rgba(0,0,0,0.05) !important;\n    opacity: 1 !important;\n}\n\n/* 高亮文字 —— 紫色 + 粗模糊虚化下划线 */\n.chat .item .touch-scope .content.left font[color=\"#DC8333\"],\n.chat .item .touch-scope .content.left font[color*=\"#ff\"],\n.chat .content .teapot-highlight {\n    color: rgb(128, 0, 128) !important;\n    font-size: 15px !important;\n    line-height: 1.5 !important;\n    font-weight: 600 !important;\n    text-shadow: none !important;\n    border-bottom: none !important;\n    text-decoration: none !important;\n    box-shadow: 0 2px 2px -1px rgba(128, 0, 128, 0.3) !important;\n}\n\n\n/* 自己的气泡 */\n.chat .chat-scope-box .scroll-view .chat-body .item .touch-scope .content.right {\n    background-color: var(--l-card-me) !important;\n    border: 2px double var(--l-sub) !important;\n    border-left: 5px solid var(--l-main) !important;\n    border-radius: 5px !important;\n    color: var(--l-text) !important;\n    box-shadow: 0 2px 4px rgba(0,0,0,0.05) !important;\n    opacity: 1 !important;\n}\n\n\n/* ==================== 3. 顶部栏 & 底部输入栏 ==================== */\n.chat .topTabbar, .chat .chat-bottom .send-msg, .chat .chat-bottom .more-scope {\n    background-color: var(--l-bg) !important;\n    box-shadow: none !important;\n}\n.chat .topTabbar { \n    border-bottom: 3px double var(--l-main) !important; \n}\n\n/* 输入框 */\n.chat .chat-bottom .chat-input-scope,#chat-input-scope{\n    position: relative;\n    background: var(--input-gradient) !important;\n    border: 2px double var(--l-sub) !important;\n    border-left: 5px solid var(--l-main) !important;\n    border-radius: 5px !important;\n    width: 100% !important;\n    transition: all 0.3s ease !important;\n    opacity: 1 !important;\n}\n/* 输入框悬浮呼吸灯（全冷调） */\n.chat .chat-bottom .chat-input-scope:hover,#chat-input-scope:hover,\n.chat .chat-bottom .chat-input-scope:focus,#chat-input-scope:focus {\n    outline: none !important;\n    border-color: var(--l-main) !important;\n    border-left: 5px solid var(--l-main) !important;\n    transform: translateY(-2px) !important;\n    animation: neon-glow 2.8s ease-in-out infinite alternate !important;\n}\n@keyframes neon-glow {\n  0% { box-shadow: 0 0 12px 2px var(--light-color); }\n  100% { box-shadow: 0 0 18px 4px var(--light-deep); }\n}\n/* 输入框内部文字 */\n.chat .chat-bottom .chat-input-scope input,\n.chat .chat-bottom .chat-input-scope textarea,\n#chat-input-scope input,\n#chat-input-scope textarea {\n    background: transparent !important;\n    border: none !important;\n    outline: none !important;\n    width: 100% !important;\n    color: var(--l-text) !important;   \n    font-size: 14px !important;\n}\n\n/* ==================== 4. 功能按钮样式 ==================== */\n.shortcut-button-scope .item,\n.reset-btn, .clear-btn, \n.export-btn, .download-btn, .save-btn,\n.more-btn, .menu-btn, .setting-btn,\n.menu-item,\n.chat-bottom .more-scope .item .item-icon {\n    background: var(--input-gradient) !important;\n    background-image: none !important;\n    border: 2px double var(--l-sub) !important;\n    border-radius: 5px !important;\n    box-shadow: 0 1px 3px rgba(38, 78, 135, 0.1) !important;\n    color: var(--l-text) !important;\n    transition: all 0.3s ease !important;\n}\n/* 按钮文字 */\n.shortcut-button-scope .item span,\n.reset-btn span, .export-btn span, .menu-item span, \n.item-title, .item-icon + span {\n    color: var(--l-text) !important;\n    font-family: \"KaiTi\", serif !important;\n    font-weight: 700 !important;\n    font-size: 13px !important;\n}\n/* 按钮悬浮效果 */\n.shortcut-button-scope .item:hover,\n.reset-btn:hover, .export-btn:hover, .menu-item:hover, .item-icon:hover {\n    background: var(--input-gradient-hover) !important;\n    border-color: var(--l-main) !important;\n    transform: translateY(-2px);\n    box-shadow: 0 3px 8px rgba(38, 78, 135, 0.2) !important;\n}\n/* 按钮内部透明 */\n.reset-btn div, .export-btn div, .menu-item div, .item-icon div {\n    background-color: transparent !important;\n    background-image: none !important;\n}\n\n/* ==================== 5. 图标统一深紫罗兰色 ==================== */\n.chat-input-scope .btn-icon div,\n.icon-back div,\n.header-meun div,\n.icon-box div,\n.edit-icon div,\n.delete-icon div,\n.reset-btn img,\n.export-btn img,\n.menu-item img,\n.item-icon img,\nimg[src*=\"ico\"],\nimg[src*=\"icon\"],\n.chat-bottom .more-scope .item .item-icon img,\n.chat-bottom .more-scope .item .item-icon div {\n    filter: var(--blue-filter) !important;\n    opacity: 1 !important;\n}\n.btn-icon div:hover,\n.item-icon:hover img,\nimg:hover {\n    opacity: 1 !important;\n    transform: scale(1.05);\n}\n\n/* ==================== 6. 滚动条样式 ==================== */\n::-webkit-scrollbar { \n    width: 6px !important;\n    height: 6px !important; \n}\n::-webkit-scrollbar-track { \n    background-color: transparent !important; \n}\n::-webkit-scrollbar-thumb { \n    background-color: var(--l-line) !important;\n    border: 1px solid var(--l-sub) !important;\n    border-radius: 0px !important;\n}\n\n/* ==================== 7. 弹窗与开关 ==================== */\n.prologue-scope .prologue-content, .msg-option-scope .msg-content-box,\n.model-setting-scope .power-scope, .token-scope .selected,\n.u-switch__node {\n    background-color: var(--l-card) !important;\n    border: 2px double rgba(38, 78, 135, 0.3) !important;\n    border-radius: 5px !important;\n    box-shadow: 0 2px 5px rgba(0,0,0,0.03) !important;\n}\n.confirm-scope, .export-modal {\n    border: 2px double var(--l-main) !important;\n    border-radius: 8px !important;\n}\n.u-switch.cursor-pointer {\n    background-color: var(--l-card) !important;\n    border: 2px double var(--l-sub) !important;\n}\n.u-switch--on { \n    background-color: var(--l-main) !important; \n}\n.u-switch__node { \n    background-color: rgb(248, 250, 252) !important; \n    border-radius: 2px !important; \n}\n/* 确认/取消按钮 */\n.confirm-scope .confirm-bottom .ok-btn,\n.reset-confirm-btn, .export-confirm-btn {\n    background-color: var(--l-main) !important;\n    color: rgb(248, 250, 252) !important;\n    border: none !important;\n}\n.confirm-scope .confirm-bottom .cancel-btn,\n.reset-cancel-btn {\n    background-color: transparent !important;\n    color: var(--l-sub) !important;\n    border: 2px double var(--l-sub) !important;\n}\n\n/* ==================== 8. 流式开关样式 ==================== */\n.power-scope,\n[class*=\"power\"],\n[class*=\"switch\"] {\n  background: var(--input-gradient) !important;\n  color: var(--l-text) !important;\n}\n\n</style>\n","scriptName":"网页美化","findRegex":"【网页美化】"}]}